MANIFEST.in
README.md
gnomeacquirer.bat
gnomeacquirer_prepare.bat
gnomeacquirerw.bat
setup.py
GNOMEAcquirerLibs/AcquisitionConfig.py
GNOMEAcquirerLibs/AcquisitionWindow.py
GNOMEAcquirerLibs/AttributeData.py
GNOMEAcquirerLibs/DataAcquire.py
GNOMEAcquirerLibs/DataAnalysis.py
GNOMEAcquirerLibs/DataBatch.py
GNOMEAcquirerLibs/DataCollected.py
GNOMEAcquirerLibs/DataToPlot.py
GNOMEAcquirerLibs/Dataset.py
GNOMEAcquirerLibs/LogFile.png
GNOMEAcquirerLibs/Meta.py
GNOMEAcquirerLibs/ViewLog.py
GNOMEAcquirerLibs/__init__.py
GNOMEAcquirerLibs/gnomeacquirer.py
GNOMEAcquirerLibs/icon-with-debug.ico
GNOMEAcquirerLibs/icon.png
gnomeacquirer.egg-info/PKG-INFO
gnomeacquirer.egg-info/SOURCES.txt
gnomeacquirer.egg-info/dependency_links.txt
gnomeacquirer.egg-info/entry_points.txt
gnomeacquirer.egg-info/top_level.txt
gnomedata/__init__.py
gnomedata/datagetter.py