Metadata-Version: 1.2
Name: gnomeacquirer
Version: 1.4.6
Summary: GNOME experiment acquisition software for magnetometers
Home-page: https://git.afach.de/budker/GNOMEBoxDataAcquisition
Author: Samer Afach
Author-email: samer@afach.de
License: UNKNOWN
Platform: UNKNOWN
Requires-Python: >=3.4
